LICENSE
MANIFEST.in
README.rst
setup.py
django_traffic_monitor.egg-info/PKG-INFO
django_traffic_monitor.egg-info/SOURCES.txt
django_traffic_monitor.egg-info/dependency_links.txt
django_traffic_monitor.egg-info/not-zip-safe
django_traffic_monitor.egg-info/requires.txt
django_traffic_monitor.egg-info/top_level.txt
docs/README.rst
docs/alarm_email.png
docs/show_traffic.png
traffic_monitor/__init__.py
traffic_monitor/admin.py
traffic_monitor/apps.py
traffic_monitor/conf.py
traffic_monitor/email.py
traffic_monitor/models.py
traffic_monitor/tools.py
traffic_monitor/urls.py
traffic_monitor/views.py
traffic_monitor/wrapper.py
traffic_monitor/locale/en/LC_MESSAGES/django.mo
traffic_monitor/locale/en/LC_MESSAGES/django.po
traffic_monitor/locale/ko/LC_MESSAGES/django.mo
traffic_monitor/locale/ko/LC_MESSAGES/django.po
traffic_monitor/migrations/0001_initial.py
traffic_monitor/migrations/0002_auto_20200302_1509.py
traffic_monitor/migrations/__init__.py
traffic_monitor/migrations/__pycache__/0001_initial.cpython-37.pyc
traffic_monitor/migrations/__pycache__/0002_auto_20200211_1244.cpython-37.pyc
traffic_monitor/migrations/__pycache__/0002_auto_20200302_1509.cpython-37.pyc
traffic_monitor/migrations/__pycache__/__init__.cpython-37.pyc
traffic_monitor/templates/traffic_monitor/alarm.html
traffic_monitor/templates/traffic_monitor/show_traffic.html